Workbook

Sheet Instructions
A1: LOOKUP FORMULA PRACTICE -- 10 EXERCISES, NO TUTORIAL
A3: The point of this drill is to fail a little and figure it out -- that's what makes it stick.
A5: How to run it:
A6: 1. Go to the 'Sales Data' tab to see the raw data, and 'Reference Tables' for the lookup tables you'll pull from.
A7: 2. Go to 'Exercises'. Each row gives you a task in plain English and tells you which cells to reference.
A8: 3. Type your formula directly into the yellow 'Your Formula' cell. Give each one a real 5-10 min attempt before you look at the hint.
A9: 4. Stuck after a real attempt? Read the 'Hint' column -- it nudges you toward the right function, it doesn't give you the formula.
A10: 5. Only after you've written something (right or wrong) for all 10, open 'Answer Key' to check yourself. Opening it first defeats the whole point of 'without watching a tutorial.'
A12: What's covered: VLOOKUP, INDEX/MATCH, XLOOKUP, IFERROR, approximate-match lookups, two-way lookups, and nested IF -- the exact set from today's Day 1 study session.

Sheet Sales Data
A1: SALES DATA -- SAMPLE SALES SHEET
A3: OrderID | B3: OrderDate | C3: Region | D3: SalesRep | E3: Product | F3: Category | G3: Units | H3: UnitPrice | I3: Revenue | J3: Status
A4: ORD-1001 | B4: 2026-06-02 | C4: Lagos | D4: Chidi Eze | E4: USB-C Hub | F4: Accessories | G4: 8 | H4: 8700 | I4: =G4*H4 -> 69600 | J4: Delivered
A5: ORD-1002 | B5: 2026-06-03 | C5: Port Harcourt | D5: Emeka Nwosu | E5: Office Chair | F5: Furniture | G5: 3 | H5: 68000 | I5: =G5*H5 -> 204000 | J5: Delivered
A6: ORD-1003 | B6: 2026-06-04 | C6: Lagos | D6: Ada Obi | E6: External SSD 1TB | F6: Storage | G6: 10 | H6: 42000 | I6: =G6*H6 -> 420000 | J6: Pending
A7: ORD-1004 | B7: 2026-06-05 | C7: Lagos | D7: Chidi Eze | E7: 27in Monitor | F7: Displays | G7: 5 | H7: 95000 | I7: =G7*H7 -> 475000 | J7: Cancelled
A8: ORD-1005 | B8: 2026-06-06 | C8: Port Harcourt | D8: Emeka Nwosu | E8: Webcam HD | F8: Peripherals | G8: 12 | H8: 15400 | I8: =G8*H8 -> 184800 | J8: Delivered
A9: ORD-1006 | B9: 2026-06-07 | C9: Lagos | D9: Ada Obi | E9: Noise Cancelling Headset | F9: Peripherals | G9: 7 | H9: 32000 | I9: =G9*H9 -> 224000 | J9: Delivered
A10: ORD-1007 | B10: 2026-06-08 | C10: Lagos | D10: Chidi Eze | E10: Mechanical Keyboard | F10: Accessories | G10: 2 | H10: 18500 | I10: =G10*H10 -> 37000 | J10: Delivered
A11: ORD-1008 | B11: 2026-06-09 | C11: Port Harcourt | D11: Emeka Nwosu | E11: Laptop Stand | F11: Accessories | G11: 9 | H11: 6300 | I11: =G11*H11 -> 56700 | J11: Pending
A12: ORD-1009 | B12: 2026-06-10 | C12: Lagos | D12: Ada Obi | E12: Standing Desk | F12: Furniture | G12: 4 | H12: 145000 | I12: =G12*H12 -> 580000 | J12: Cancelled
A13: ORD-1010 | B13: 2026-06-11 | C13: Lagos | D13: Chidi Eze | E13: Wireless Mouse | F13: Accessories | G13: 11 | H13: 5200 | I13: =G13*H13 -> 57200 | J13: Delivered
A14: ORD-1011 | B14: 2026-06-12 | C14: Port Harcourt | D14: Emeka Nwosu | E14: USB-C Hub | F14: Accessories | G14: 6 | H14: 8700 | I14: =G14*H14 -> 52200 | J14: Delivered
A15: ORD-1012 | B15: 2026-06-13 | C15: Lagos | D15: Ada Obi | E15: Office Chair | F15: Furniture | G15: 1 | H15: 68000 | I15: =G15*H15 -> 68000 | J15: Delivered
... A33: ORD-1030 | B33: 2026-06-03 | C33: Lagos | D33: Ada Obi | E33: Wireless Mouse | F33: Accessories | G33: 7 | H33: 5200 | I33: =G33*H33 -> 36400 | J33: Delivered

Sheet Reference Tables
A1: REFERENCE TABLES
A3: Product Price List | F3: Sales Rep Directory
A4: Product | B4: Category | C4: UnitPrice | D4: ReorderLevel | F4: SalesRep | G4: Region | H4: MonthlyTarget | I4: Manager
A5: Wireless Mouse | B5: Accessories | C5: 5200 | D5: 10 | F5: Ada Obi | G5: Lagos | H5: 500000 | I5: T. Balogun
A6: Mechanical Keyboard | B6: Accessories | C6: 18500 | D6: 11 | F6: Bola Ade | G6: Abuja | H6: 525000 | I6: T. Balogun
A7: 27in Monitor | B7: Displays | C7: 95000 | D7: 12 | F7: Chidi Eze | G7: Lagos | H7: 550000 | I7: K. Ibrahim
A8: USB-C Hub | B8: Accessories | C8: 8700 | D8: 13 | F8: Fatima Bello | G8: Kano | H8: 575000 | I8: K. Ibrahim
A9: Laptop Stand | B9: Accessories | C9: 6300 | D9: 14 | F9: Emeka Nwosu | G9: Port Harcourt | H9: 600000 | I9: T. Balogun
A10: Webcam HD | B10: Peripherals | C10: 15400 | D10: 15 | F10: Grace Udo | G10: Abuja | H10: 625000 | I10: K. Ibrahim
A11: Office Chair | B11: Furniture | C11: 68000 | D11: 16
A12: Standing Desk | B12: Furniture | C12: 145000 | D12: 17
A13: Noise Cancelling Headset | B13: Peripherals | C13: 32000 | D13: 18
A14: External SSD 1TB | B14: Storage | C14: 42000 | D14: 19
A17: Discount Tiers (by Units Ordered)
A18: MinUnits | B18: Discount%
A19: 0 | B19: 0
A20: 5 | B20: 0.05
A21: 8 | B21: 0.08
A22: 10 | B22: 0.12

Sheet Exercises
A1: 10 LOOKUP EXERCISES -- WRITE THE FORMULA YOURSELF
A2: Yellow 'Input' cells are given. Yellow 'Your Formula' cells are where you write your formula. Don't peek at 'Answer Key' until you've attempted all 10.
A3: # | B3: Skill Focus | C3: Task | D3: Input 1 | E3: Input 2 | F3: Your Formula | G3: Hint
A4: 1 | B4: VLOOKUP (exact match) | C4: Look up the Category for the product named in D4, using the Product Price List on 'Reference Tables'. | D4: 27in Monitor | F4: =VLOOKUP(D4,'Reference Tables'!A4:B14,2,) -> Displays | G4: Return an exact-match VLOOKUP. Table array is 'Reference Tables'!A5:D14 -- what column number is Category in?
A5: 2 | B5: INDEX/MATCH | C5: Look up the UnitPrice for the product named in D5, using INDEX/MATCH instead of VLOOKUP. | D5: External SSD 1TB | F5: =INDEX('Reference Tables'!C4:C14,MATCH(Exercises!D5,'Reference Tables'!A4:A14,0)) -> 42000 | G5: MATCH finds the row position of the product in the Product column; INDEX pulls from the UnitPrice column using that position.
A6: 3 | B6: XLOOKUP | C6: Look up the Region for the sales rep named in D6, using the Sales Rep Directory. | D6: Chidi Eze | F6: =_xlfn.XLOOKUP(D6,'Reference Tables'!F4:F10,'Reference Tables'!G4:G10) -> Lagos | G6: XLOOKUP(lookup_value, lookup_array, return_array) -- lookup_array is the SalesRep column, return_array is the Region column.
A7: 4 | B7: XLOOKUP with if_not_found | C7: Look up the Category for the product named in D7 (it does not exist in the list). Return 'Not Found' instead of an error. | D7: Bluetooth Speaker | F7: =_xlfn.XLOOKUP(D7,'Reference Tables'!A4:A14,'Reference Tables'!B4:B14,"Not Found") -> Not Found | G7: XLOOKUP has a 4th argument built for exactly this -- you don't need IFERROR at all here.
A8: 5 | B8: IFERROR + VLOOKUP | C8: Look up the MonthlyTarget for the sales rep named in D8 (it may not exist). If not found, show 'Check Name'. | D8: Uche Nnamdi | F8: =IFERROR(VLOOKUP(D8,'Reference Tables'!F4:H10,3,FALSE),"Check Name") -> Check Name | G8: Wrap a normal VLOOKUP inside IFERROR(..., "Check Name").
A9: 6 | B9: Two-way INDEX/MATCH | C9: On 'Sales Data', return the value for the OrderID in D9 at the column named in E9, using two MATCH functions inside one INDEX. | D9: ORD-1015 | E9: Revenue | F9: =INDEX('Sales Data'!A3:J33,MATCH(Exercises!D9,'Sales Data'!A3:A33,0),MATCH(Exercises!E9,'Sales Data'!A3:J3,0)) -> 154000 | G9: INDEX(data_range, MATCH(row_value, id_column, 0), MATCH(column_value, header_row, 0)) -- match once for the row, once for the column.
A10: 7 | B10: Approximate-match VLOOKUP | C10: Look up the Discount% for the Units value in D10, using the Discount Tiers table with a range (approximate) lookup. | D10: 9 | F10: =VLOOKUP(D10,'Reference Tables'!A18:B22,2,TRUE) -> 0.08 | G10: The 4th argument of VLOOKUP controls exact vs. approximate match. The tier table must stay sorted ascending for this to work.
A11: 8 | B11: Nested IF | C11: Classify the Revenue in D11 as 'Small' (<20,000), 'Medium' (20,000-80,000), or 'Large' (>80,000). | D11: 45000 | F11: =IF(D11<20000,"small",IF(D11<=80000,"Medium","Large")) -> Medium | G11: IF(condition1, result1, IF(condition2, result2, result3)) -- two IFs nested, three possible outcomes.
A12: 9 | B12: Nested IF + AND | C12: Given Region in D12 and Revenue in E12, return 'Priority' if Region is 'Lagos' AND Revenue > 50,000, else 'Standard'. | D12: Lagos | E12: 62000 | F12: =IF(AND(D12,E12>50000),"Priority","Standard") -> Priority | G12: IF(AND(condition1, condition2), "Priority", "Standard").
A13: 10 | B13: XLOOKUP + IFERROR | C13: Look up the Manager for the sales rep named in D13 (may not exist). If not found, return 'Unassigned'. | D13: Grace Udo | F13: =_xlfn.XLOOKUP(D13,'Reference Tables'!F4:F10,'Reference Tables'!I4:I10) -> K. Ibrahim | G13: Either use XLOOKUP's built-in if_not_found argument, or wrap XLOOKUP in IFERROR -- try both and see which is cleaner.

Sheet Answer Key
A1: ANSWER KEY -- CHECK YOURSELF, DON'T COPY FIRST
A2: These are one correct way to solve each exercise -- not the only way. If your formula returns the same result via a different route, that's still correct.
A3: # | B3: Skill Focus | C3: Working Formula (this cell computes and displays the real answer when opened) | D3: XLOOKUP version (for real Excel/Google Sheets)
A4: 1 | B4: VLOOKUP (exact match) | C4: =VLOOKUP(Exercises!D4,'Reference Tables'!A5:D14,2,FALSE()) -> Displays | D4: (same function used above)
A5: 2 | B5: INDEX/MATCH | C5: =INDEX('Reference Tables'!C5:C14,MATCH(Exercises!D5,'Reference Tables'!A5:A14,0)) -> 42000 | D5: (same function used above)
A6: 3 | B6: XLOOKUP | C6: =INDEX('Reference Tables'!G5:G10,MATCH(Exercises!D6,'Reference Tables'!F5:F10,0)) -> Lagos | D6: XLOOKUP(D6,'Reference Tables'!F5:F10,'Reference Tables'!G5:G10)
A7: 4 | B7: XLOOKUP with if_not_found | C7: =IFERROR(INDEX('Reference Tables'!B5:B14,MATCH(Exercises!D7,'Reference Tables'!A5:A14,0)),"Not Found") -> Not Found | D7: XLOOKUP(D7,'Reference Tables'!A5:A14,'Reference Tables'!B5:B14,"Not Found")
A8: 5 | B8: IFERROR + VLOOKUP | C8: =IFERROR(VLOOKUP(Exercises!D8,'Reference Tables'!F5:I10,3,FALSE()),"Check Name") -> Check Name | D8: (same function used above)
A9: 6 | B9: Two-way INDEX/MATCH | C9: =INDEX('Sales Data'!A4:J33,MATCH(Exercises!D9,'Sales Data'!A4:A33,0),MATCH(Exercises!E9,'Sales Data'!A3:J3,0)) -> 154000 | D9: (same function used above)
A10: 7 | B10: Approximate-match VLOOKUP | C10: =VLOOKUP(Exercises!D10,'Reference Tables'!A19:B22,2,TRUE()) -> 0.08 | D10: (same function used above)
A11: 8 | B11: Nested IF | C11: =IF(Exercises!D11<20000,"Small",IF(Exercises!D11<=80000,"Medium","Large")) -> Medium | D11: (same function used above)
A12: 9 | B12: Nested IF + AND | C12: =IF(AND(Exercises!D12="Lagos",Exercises!E12>50000),"Priority","Standard") -> Priority | D12: (same function used above)
A13: 10 | B13: XLOOKUP + IFERROR | C13: =IFERROR(INDEX('Reference Tables'!I5:I10,MATCH(Exercises!D13,'Reference Tables'!F5:F10,0)),"Unassigned") -> K. Ibrahim | D13: XLOOKUP(D13,'Reference Tables'!F5:F10,'Reference Tables'!I5:I10,"Unassigned")
